tradier_api/__init__.py
tradier_api/_core_types.py
tradier_api/tradier_config.py
tradier_api/tradier_controllers.py
tradier_api/tradier_params.py
tradier_api/tradier_streams.py
tradier_api/tradier_types.py
tradier_api-0.1.4.dist-info/LICENSE
tradier_api-0.1.4.dist-info/METADATA
tradier_api-0.1.4.dist-info/WHEEL
tradier_api-0.1.4.dist-info/top_level.txt
tradier_api-0.1.4.dist-info/RECORD
