Metadata-Version: 2.1
Name: tradier_api
Version: 0.1.4
Summary: A Python library for the Tradier API
Home-page: https://github.com/kickshawprogrammer/tradier_api
Author: KickshawProgrammer
Author-email: kickshawprogrammer@gmail.com
License: MIT
Project-URL: Documentation, https://github.com/kickshawprogrammer/tradier_api/wiki
Project-URL: Source, https://github.com/kickshawprogrammer/tradier_api
Project-URL: Bug Tracker, https://github.com/kickshawprogrammer/tradier_api/issues
Classifier: License :: OSI Approved :: MIT License
Classifier: Programming Language :: Python :: 3
Classifier: License :: Other/Proprietary License
Classifier: Operating System :: OS Independent
License-File: LICENSE
Requires-Dist: requests>=2.32.3
Requires-Dist: websockets>=14.1
